{
  "name": "Larry Waters",
  "age": 60,
  "address": {
    "street": "Makwu Trail",
    "city": "Hihfoole",
    "state": "FL",
    "zip": "65503"
  },
  "contact": {
    "phone": "(587) 568-3924",
    "servicePhone": "800456276"
  },
  "birthday": "1974-07-14T05:59:18.167Z",
  "ip": "234.161.101.97",
  "foo": "bar",
  "profile": {
    "about": "Lil gegmeap leted foronveg izi loncurno zur otocapuh jawajhi wi ruse fe tef. Abeuce do cusafe cesvav utban jidfi sulje sugeha huzjup meutnuc ogiol uladul ew wofmutak wuj ap cafpin. Otzuk ja nep uwiav wu dugzoshi odezu jiiwjeb deidi does wobuav oduvezof aletozsa pe gacogij. Rob sadobi tevetu ew kufeclow wi vif tozhivuso orwe wevzah erwe zivcez wegani ron rufid kugoko.",
    "bio": "Harko resod am kipvemvo dec zanuke uwi faeneti hu gos garacvu lubnipri uhiunreb. Luj zonafa fuvdu fa le sekfunmi lefoh jazhu gute lawizitaw hove onopahtar. Ejawecobo wompuwid zijav hutsem bipe cov wigipbe joc hogunuz lovihen heneg ansuj wiw. Otavo jar ho ramcodvit dejabo selmofho puhwipru pu rupa bugeb burkula bem ideigdo huge."
  },
  "apiKey": "9a859bcf378841237af496a25c751fdec6c2c684bbb6e257503e2b1dceb7c94c",
  "currency": {
    "code": "SCR",
    "name": "Seychelles Rupee"
  }
}